ZetcodeShujukuJiaochengChuyi/README.md
ZetcodeShujukuJiaochengChuyi/__init__.py
ZetcodeShujukuJiaochengChuyi/__main__.py
ZetcodeShujukuJiaochengChuyi/file.epub
ZetcodeShujukuJiaochengChuyi/index.html
ZetcodeShujukuJiaochengChuyi/css/__init__.py
ZetcodeShujukuJiaochengChuyi/css/annotations.css
ZetcodeShujukuJiaochengChuyi/css/main.css
ZetcodeShujukuJiaochengChuyi/css/normalize.css
ZetcodeShujukuJiaochengChuyi/css/popup.css
ZetcodeShujukuJiaochengChuyi/font/__init__.py
ZetcodeShujukuJiaochengChuyi/font/fontello.eot
ZetcodeShujukuJiaochengChuyi/font/fontello.svg
ZetcodeShujukuJiaochengChuyi/font/fontello.ttf
ZetcodeShujukuJiaochengChuyi/font/fontello.woff
ZetcodeShujukuJiaochengChuyi/img/__init__.py
ZetcodeShujukuJiaochengChuyi/img/annotator-glyph-sprite.png
ZetcodeShujukuJiaochengChuyi/img/annotator-icon-sprite.png
ZetcodeShujukuJiaochengChuyi/img/apple-touch-icon.png
ZetcodeShujukuJiaochengChuyi/img/cancelfullscreen.png
ZetcodeShujukuJiaochengChuyi/img/close.png
ZetcodeShujukuJiaochengChuyi/img/fullscreen.png
ZetcodeShujukuJiaochengChuyi/img/loader.gif
ZetcodeShujukuJiaochengChuyi/img/menu-icon.png
ZetcodeShujukuJiaochengChuyi/img/save.png
ZetcodeShujukuJiaochengChuyi/img/saved.png
ZetcodeShujukuJiaochengChuyi/img/settings-s.png
ZetcodeShujukuJiaochengChuyi/img/settings.png
ZetcodeShujukuJiaochengChuyi/img/star.png
ZetcodeShujukuJiaochengChuyi/js/__init__.py
ZetcodeShujukuJiaochengChuyi/js/epub.js
ZetcodeShujukuJiaochengChuyi/js/epub.min.js
ZetcodeShujukuJiaochengChuyi/js/epub.min.map
ZetcodeShujukuJiaochengChuyi/js/hooks.min.js
ZetcodeShujukuJiaochengChuyi/js/hooks.min.map
ZetcodeShujukuJiaochengChuyi/js/reader.js
ZetcodeShujukuJiaochengChuyi/js/reader.js.map
ZetcodeShujukuJiaochengChuyi/js/reader.min.js
ZetcodeShujukuJiaochengChuyi/js/reader.min.map
ZetcodeShujukuJiaochengChuyi/js/hooks/__init__.py
ZetcodeShujukuJiaochengChuyi/js/hooks/extensions/__init__.py
ZetcodeShujukuJiaochengChuyi/js/hooks/extensions/highlight.js
zetcode_shujuku_jiaocheng_chuyi-2024.3.5.0.dist-info/METADATA
zetcode_shujuku_jiaocheng_chuyi-2024.3.5.0.dist-info/WHEEL
zetcode_shujuku_jiaocheng_chuyi-2024.3.5.0.dist-info/entry_points.txt
zetcode_shujuku_jiaocheng_chuyi-2024.3.5.0.dist-info/top_level.txt
zetcode_shujuku_jiaocheng_chuyi-2024.3.5.0.dist-info/RECORD
